[
    {
        "Name": "Baby Peach",
        "Name_JP": "ベビィピーチ",
        "Road": 3,
        "Terrain": 3,
        "Water": 3,
        "Unknown": 3,
        "Accel": 10,
        "Weight": 3,
        "Handling": 9
    },
    {
        "Name": "Baby Daisy",
        "Name_JP": "ベビィデイジー",
        "Road": 3,
        "Terrain": 3,
        "Water": 3,
        "Unknown": 3,
        "Accel": 10,
        "Weight": 3,
        "Handling": 9
    },
    {
        "Name": "Swooper",
        "Name_JP": "バサバサ",
        "Road": 3,
        "Terrain": 3,
        "Water": 3,
        "Unknown": 3,
        "Accel": 10,
        "Weight": 3,
        "Handling": 9
    },
    {
        "Name": "Para-Biddybud",
        "Name_JP": "パタテンテン",
        "Road": 3,
        "Terrain": 3,
        "Water": 3,
        "Unknown": 3,
        "Accel": 10,
        "Weight": 3,
        "Handling": 9
    },
    {
        "Name": "Baby Mario",
        "Name_JP": "ベビィマリオ",
        "Road": 4,
        "Terrain": 3,
        "Water": 3,
        "Unknown": 3,
        "Accel": 9,
        "Weight": 4,
        "Handling": 9
    },
    {
        "Name": "Goomba",
        "Name_JP": "クリボー",
        "Road": 4,
        "Terrain": 3,
        "Water": 3,
        "Unknown": 3,
        "Accel": 9,
        "Weight": 4,
        "Handling": 9
    },
    {
        "Name": "Spike",
        "Name_JP": "ガボン",
        "Road": 4,
        "Terrain": 3,
        "Water": 3,
        "Unknown": 3,
        "Accel": 9,
        "Weight": 4,
        "Handling": 9
    },
    {
        "Name": "Baby Luigi",
        "Name_JP": "ベビィルイージ",
        "Road": 3,
        "Terrain": 4,
        "Water": 3,
        "Unknown": 3,
        "Accel": 9,
        "Weight": 4,
        "Handling": 9
    },
    {
        "Name": "Dry Bones",
        "Name_JP": "カロン",
        "Road": 3,
        "Terrain": 4,
        "Water": 3,
        "Unknown": 3,
        "Accel": 9,
        "Weight": 4,
        "Handling": 9
    },
    {
        "Name": "Peepa",
        "Name_JP": "テレン",
        "Road": 3,
        "Terrain": 4,
        "Water": 3,
        "Unknown": 3,
        "Accel": 9,
        "Weight": 4,
        "Handling": 9
    },
    {
        "Name": "Baby Rosalina",
        "Name_JP": "ベビィロゼッタ",
        "Road": 3,
        "Terrain": 3,
        "Water": 4,
        "Unknown": 3,
        "Accel": 9,
        "Weight": 4,
        "Handling": 9
    },
    {
        "Name": "Sidestepper",
        "Name_JP": "カニ",
        "Road": 3,
        "Terrain": 3,
        "Water": 4,
        "Unknown": 3,
        "Accel": 9,
        "Weight": 4,
        "Handling": 9
    },
    {
        "Name": "Fishbone",
        "Name_JP": "フィッシュボーン",
        "Road": 3,
        "Terrain": 3,
        "Water": 4,
        "Unknown": 3,
        "Accel": 9,
        "Weight": 4,
        "Handling": 9
    },
    {
        "Name": "Toadette",
        "Name_JP": "キノピコ",
        "Road": 5,
        "Terrain": 4,
        "Water": 4,
        "Unknown": 4,
        "Accel": 8,
        "Weight": 5,
        "Handling": 8
    },
    {
        "Name": "Nabbit",
        "Name_JP": "トッテン",
        "Road": 5,
        "Terrain": 4,
        "Water": 4,
        "Unknown": 4,
        "Accel": 8,
        "Weight": 5,
        "Handling": 8
    },
    {
        "Name": "Toad",
        "Name_JP": "キノピオ",
        "Road": 4,
        "Terrain": 5,
        "Water": 4,
        "Unknown": 4,
        "Accel": 8,
        "Weight": 5,
        "Handling": 8
    },
    {
        "Name": "Shy Guy",
        "Name_JP": "ヘイホー",
        "Road": 4,
        "Terrain": 5,
        "Water": 4,
        "Unknown": 4,
        "Accel": 8,
        "Weight": 5,
        "Handling": 8
    },
    {
        "Name": "Stingby",
        "Name_JP": "ハッチン",
        "Road": 4,
        "Terrain": 5,
        "Water": 4,
        "Unknown": 4,
        "Accel": 8,
        "Weight": 5,
        "Handling": 8
    },
    {
        "Name": "Koopa Troopa",
        "Name_JP": "ノコノコ",
        "Road": 4,
        "Terrain": 4,
        "Water": 5,
        "Unknown": 4,
        "Accel": 8,
        "Weight": 5,
        "Handling": 8
    },
    {
        "Name": "Lakitu",
        "Name_JP": "ジュゲム",
        "Road": 4,
        "Terrain": 4,
        "Water": 5,
        "Unknown": 4,
        "Accel": 8,
        "Weight": 5,
        "Handling": 8
    },
    {
        "Name": "Cheep Cheep",
        "Name_JP": "プクプク",
        "Road": 4,
        "Terrain": 4,
        "Water": 5,
        "Unknown": 4,
        "Accel": 8,
        "Weight": 5,
        "Handling": 8
    },
    {
        "Name": "Peach",
        "Name_JP": "ピーチ",
        "Road": 6,
        "Terrain": 5,
        "Water": 5,
        "Unknown": 5,
        "Accel": 7,
        "Weight": 6,
        "Handling": 7
    },
    {
        "Name": "Daisy",
        "Name_JP": "デイジー",
        "Road": 6,
        "Terrain": 5,
        "Water": 5,
        "Unknown": 5,
        "Accel": 7,
        "Weight": 6,
        "Handling": 7
    },
    {
        "Name": "Coin Coffer",
        "Name_JP": "ガマネー",
        "Road": 6,
        "Terrain": 5,
        "Water": 5,
        "Unknown": 5,
        "Accel": 7,
        "Weight": 6,
        "Handling": 7
    },
    {
        "Name": "Yoshi",
        "Name_JP": "ヨッシー",
        "Road": 5,
        "Terrain": 6,
        "Water": 5,
        "Unknown": 5,
        "Accel": 7,
        "Weight": 6,
        "Handling": 7
    },
    {
        "Name": "Monty Mole",
        "Name_JP": "チョロプー",
        "Road": 5,
        "Terrain": 6,
        "Water": 5,
        "Unknown": 5,
        "Accel": 7,
        "Weight": 6,
        "Handling": 7
    },
    {
        "Name": "Bowser Jr.",
        "Name_JP": "クッパJr.",
        "Road": 5,
        "Terrain": 5,
        "Water": 6,
        "Unknown": 5,
        "Accel": 7,
        "Weight": 6,
        "Handling": 7
    },
    {
        "Name": "Dolphin",
        "Name_JP": "イルカ",
        "Road": 5,
        "Terrain": 5,
        "Water": 6,
        "Unknown": 5,
        "Accel": 7,
        "Weight": 6,
        "Handling": 7
    },
    {
        "Name": "Mario",
        "Name_JP": "マリオ",
        "Road": 7,
        "Terrain": 6,
        "Water": 6,
        "Unknown": 6,
        "Accel": 6,
        "Weight": 7,
        "Handling": 6
    },
    {
        "Name": "Rocky Wrench",
        "Name_JP": "プー",
        "Road": 7,
        "Terrain": 6,
        "Water": 6,
        "Unknown": 6,
        "Accel": 6,
        "Weight": 7,
        "Handling": 6
    },
    {
        "Name": "Luigi",
        "Name_JP": "ルイージ",
        "Road": 6,
        "Terrain": 7,
        "Water": 6,
        "Unknown": 6,
        "Accel": 6,
        "Weight": 7,
        "Handling": 6
    },
    {
        "Name": "Hammer Bro",
        "Name_JP": "ハンマーブロス",
        "Road": 6,
        "Terrain": 7,
        "Water": 6,
        "Unknown": 6,
        "Accel": 6,
        "Weight": 7,
        "Handling": 6
    },
    {
        "Name": "Pokey",
        "Name_JP": "サンボ",
        "Road": 6,
        "Terrain": 7,
        "Water": 6,
        "Unknown": 6,
        "Accel": 6,
        "Weight": 7,
        "Handling": 6
    },
    {
        "Name": "Birdo",
        "Name_JP": "キャサリン",
        "Road": 6,
        "Terrain": 6,
        "Water": 7,
        "Unknown": 6,
        "Accel": 6,
        "Weight": 7,
        "Handling": 6
    },
    {
        "Name": "Penguin",
        "Name_JP": "ペンギン",
        "Road": 6,
        "Terrain": 6,
        "Water": 7,
        "Unknown": 6,
        "Accel": 6,
        "Weight": 7,
        "Handling": 6
    },
    {
        "Name": "Pauline",
        "Name_JP": "ポリーン",
        "Road": 8,
        "Terrain": 7,
        "Water": 7,
        "Unknown": 7,
        "Accel": 5,
        "Weight": 8,
        "Handling": 5
    },
    {
        "Name": "Snowman",
        "Name_JP": "ゆきだるま",
        "Road": 8,
        "Terrain": 7,
        "Water": 7,
        "Unknown": 7,
        "Accel": 5,
        "Weight": 8,
        "Handling": 5
    },
    {
        "Name": "Piranha Plant",
        "Name_JP": "パックンフラワー",
        "Road": 8,
        "Terrain": 7,
        "Water": 7,
        "Unknown": 7,
        "Accel": 5,
        "Weight": 8,
        "Handling": 5
    },
    {
        "Name": "King Boo",
        "Name_JP": "キングテレサ",
        "Road": 7,
        "Terrain": 8,
        "Water": 7,
        "Unknown": 7,
        "Accel": 5,
        "Weight": 8,
        "Handling": 5
    },
    {
        "Name": "Conkdor",
        "Name_JP": "ツッコンドル",
        "Road": 7,
        "Terrain": 8,
        "Water": 7,
        "Unknown": 7,
        "Accel": 5,
        "Weight": 8,
        "Handling": 5
    },
    {
        "Name": "Rosalina",
        "Name_JP": "ロゼッタ",
        "Road": 7,
        "Terrain": 7,
        "Water": 8,
        "Unknown": 7,
        "Accel": 5,
        "Weight": 8,
        "Handling": 5
    },
    {
        "Name": "Cataquack",
        "Name_JP": "ポイハナ",
        "Road": 7,
        "Terrain": 7,
        "Water": 8,
        "Unknown": 7,
        "Accel": 5,
        "Weight": 8,
        "Handling": 5
    },
    {
        "Name": "Wario",
        "Name_JP": "ワリオ",
        "Road": 9,
        "Terrain": 8,
        "Water": 8,
        "Unknown": 8,
        "Accel": 4,
        "Weight": 9,
        "Handling": 4
    },
    {
        "Name": "Wiggler",
        "Name_JP": "ハナチャン",
        "Road": 9,
        "Terrain": 8,
        "Water": 8,
        "Unknown": 8,
        "Accel": 4,
        "Weight": 9,
        "Handling": 4
    },
    {
        "Name": "Moo Moo",
        "Name_JP": "ウシ",
        "Road": 8,
        "Terrain": 9,
        "Water": 8,
        "Unknown": 8,
        "Accel": 4,
        "Weight": 9,
        "Handling": 4
    },
    {
        "Name": "Donkey Kong",
        "Name_JP": "ドンキーコング",
        "Road": 8,
        "Terrain": 9,
        "Water": 8,
        "Unknown": 8,
        "Accel": 4,
        "Weight": 9,
        "Handling": 4
    },
    {
        "Name": "Chargin' Chuck",
        "Name_JP": "ブル",
        "Road": 8,
        "Terrain": 9,
        "Water": 8,
        "Unknown": 8,
        "Accel": 4,
        "Weight": 9,
        "Handling": 4
    },
    {
        "Name": "Waluigi",
        "Name_JP": "ワルイージ",
        "Road": 8,
        "Terrain": 8,
        "Water": 9,
        "Unknown": 8,
        "Accel": 4,
        "Weight": 9,
        "Handling": 4
    },
    {
        "Name": "Pianta",
        "Name_JP": "モンテ",
        "Road": 8,
        "Terrain": 8,
        "Water": 9,
        "Unknown": 8,
        "Accel": 4,
        "Weight": 9,
        "Handling": 4
    },
    {
        "Name": "Bowser",
        "Name_JP": "クッパ",
        "Road": 9,
        "Terrain": 9,
        "Water": 9,
        "Unknown": 9,
        "Accel": 3,
        "Weight": 10,
        "Handling": 3
    }
]